CHANGES.rst
CONTRIBUTORS.rst
LICENSE
MANIFEST.in
README.md
pytest_sugar.py
setup.cfg
setup.py
test_sugar.py
tox.ini
pytest_saccharin.egg-info/PKG-INFO
pytest_saccharin.egg-info/SOURCES.txt
pytest_saccharin.egg-info/dependency_links.txt
pytest_saccharin.egg-info/entry_points.txt
pytest_saccharin.egg-info/not-zip-safe
pytest_saccharin.egg-info/requires.txt
pytest_saccharin.egg-info/top_level.txt