Metadata-Version: 2.1
Name: pytest-saccharin
Version: 0.9.5
Summary: pytest-saccharin is a updated fork of pytest-sugar, a plugin for pytest that changes the default look and feel of pytest (e.g. progressbar, show tests that fail instantly).
Home-page: https://github.com/DisruptiveLabs/pytest-saccharin/
Author: DisruptiveLabs, Teemu, Janne Vanhala and others
Author-email: github@comanage.com, orkkiolento@gmail.com, janne.vanhala@gmail.com
License: BSD
Project-URL: Source, https://github.com/DisruptiveLabs/pytest-saccharin/
Project-URL: Tracker, https://github.com/DisruptiveLabs/pytest-saccharin/issues
Platform: any
Classifier: Development Status :: 3 - Alpha
Classifier: Intended Audience :: Developers
Classifier: License :: OSI Approved :: BSD License
Classifier: Operating System :: POSIX
Classifier: Operating System :: Microsoft :: Windows
Classifier: Operating System :: MacOS :: MacOS X
Classifier: Topic :: Software Development :: Testing
Classifier: Topic :: Software Development :: Libraries
Classifier: Topic :: Utilities
Classifier: Programming Language :: Python :: 2
Classifier: Programming Language :: Python :: 2.7
Classifier: Programming Language :: Python :: 3
Classifier: Programming Language :: Python :: 3.4
Classifier: Programming Language :: Python :: 3.5
Classifier: Programming Language :: Python :: 3.6
Classifier: Programming Language :: Python :: 3.7
Classifier: Programming Language :: Python :: 3.8
Classifier: Programming Language :: Python :: Implementation :: PyPy
License-File: LICENSE
